postbin/__init__.py
postbin/__main__.py
postbin/v2/__init__.py
postbin/v2/errors.py
PyHasteBin-1.2.6.dist-info/LICENSE
PyHasteBin-1.2.6.dist-info/METADATA
PyHasteBin-1.2.6.dist-info/WHEEL
PyHasteBin-1.2.6.dist-info/top_level.txt
PyHasteBin-1.2.6.dist-info/RECORD
