Metadata-Version: 2.1
Name: PyHasteBin
Version: 1.2.6
Summary: A simple two-function program that POSTs to hastebin
Home-page: https://github.com/ytcalifax/PyHasteBin
Author: EEKIM10, ytcalifax
Author-email: kcustom.businessonly@gmail.com
License: MIT
Requires-Python: >=3.6
License-File: LICENSE
Provides-Extra: cli
Requires-Dist: webbrowser ; extra == 'cli'
